pyboxes/__init__.py
pyboxes/__main__.py
pyboxes/commands/__init__.py
pyboxes/commands/asyncdown.py
pyboxes/commands/gfile.py
pyboxes/commands/gfolder.py
pyboxes/commands/slack.py
pyboxes/py.typed
pyboxes/utils.py
pyboxes-2.3.1.dist-info/entry_points.txt
pyboxes-2.3.1.dist-info/LICENSE
pyboxes-2.3.1.dist-info/WHEEL
pyboxes-2.3.1.dist-info/METADATA
pyboxes-2.3.1.dist-info/RECORD
