Metadata-Version: 2.1
Name: pyboxes
Version: 2.3.1
Summary: Pyboxes
Home-page: https://github.com/cauliyang/pybox
License: MIT
Author: yangli
Author-email: yangyang.li@northwestern.edu
Requires-Python: >=3.9,<4.0
Classifier: Development Status :: 2 - Pre-Alpha
Classifier: Environment :: Console
Classifier: License :: OSI Approved :: MIT License
Classifier: Programming Language :: Python :: 3
Classifier: Programming Language :: Python :: 3.10
Classifier: Programming Language :: Python :: 3.9
Requires-Dist: aiofiles (>=0.8,<22.2)
Requires-Dist: aiohttp (>=3.8.1,<4.0.0)
Requires-Dist: click (>=8.0.1,<9.0.0)
Requires-Dist: click-help-colors (>=0.9.1,<0.10.0)
Requires-Dist: google-api-python-client (>=2.37.0,<3.0.0)
Requires-Dist: google-auth-httplib2 (>=0.1.0,<0.2.0)
Requires-Dist: google-auth-oauthlib (>=0.4.6,<0.6.0)
Requires-Dist: linkify-it-py (>=2.0.0,<3.0.0)
Requires-Dist: loguru (>=0.5.3,<0.7.0)
Requires-Dist: requests (>=2.26.0,<3.0.0)
Requires-Dist: types-aiofiles (>=0.8.8,<22.2.0)
Requires-Dist: types-requests (>=2.27.25,<3.0.0)
Project-URL: Changelog, https://github.com/cauliyang/pybox/releases
Project-URL: Documentation, https://pyboxes.readthedocs.io
Project-URL: Repository, https://github.com/cauliyang/pybox
